tmux_utils/__init__.py
tmux_utils/py.typed
tmux_utils/tm_session_root.py
tmux_utils/tm_sessions.py
tmux_utils-0.1.5.data/scripts/tm
tmux_utils-0.1.5.data/scripts/tm-break-pane
tmux_utils-0.1.5.data/scripts/tm-copy
tmux_utils-0.1.5.data/scripts/tm-fix-layout
tmux_utils-0.1.5.data/scripts/tm-home
tmux_utils-0.1.5.data/scripts/tm-init
tmux_utils-0.1.5.data/scripts/tm-init-athena
tmux_utils-0.1.5.data/scripts/tm-init-prime
tmux_utils-0.1.5.data/scripts/tm-init-remote
tmux_utils-0.1.5.data/scripts/tm-join-pane
tmux_utils-0.1.5.data/scripts/tm-kill
tmux_utils-0.1.5.data/scripts/tm-new-window
tmux_utils-0.1.5.data/scripts/tm-select-pane
tmux_utils-0.1.5.data/scripts/tm-send
tmux_utils-0.1.5.data/scripts/tm-session-name
tmux_utils-0.1.5.data/scripts/tm-socket
tmux_utils-0.1.5.data/scripts/tm-zoom
tmux_utils-0.1.5.dist-info/METADATA
tmux_utils-0.1.5.dist-info/WHEEL
tmux_utils-0.1.5.dist-info/entry_points.txt
tmux_utils-0.1.5.dist-info/top_level.txt
tmux_utils-0.1.5.dist-info/RECORD
