Metadata-Version: 2.1
Name: tmux-utils
Version: 0.1.5
Summary: Helper scripts for working with tmux more efficiently.
Home-page: https://github.com/bbugyi200/tmux-utils
Author: Bryan M Bugyi
Author-email: bryanbugyi34@gmail.com
License: MIT license
Platform: UNKNOWN
Classifier: Development Status :: 3 - Alpha
Classifier: Intended Audience :: Developers
Classifier: License :: OSI Approved :: MIT License
Classifier: Natural Language :: English
Classifier: Programming Language :: Python :: 3
Classifier: Programming Language :: Python :: 3.8
Classifier: Programming Language :: Python :: 3.9
Classifier: Programming Language :: Python :: 3.10
Requires-Python: >=3.8
Requires-Dist: bugyi.tools (~=0.2.2)
Requires-Dist: bolton-clack (~=0.3.1)
Requires-Dist: bolton-logrus (~=0.1.0)
